meajur.py
meajur/meajur.py
meajur-0.0.33.dist-info/LICENSE
meajur-0.0.33.dist-info/METADATA
meajur-0.0.33.dist-info/WHEEL
meajur-0.0.33.dist-info/entry_points.txt
meajur-0.0.33.dist-info/top_level.txt
meajur-0.0.33.dist-info/RECORD
